{
    "uid": "0xbbf8653003df11ea98ae0205857feb80",
    "alias_with_namespace": "axenox.deployer.console",
    "menu_parent_page_selector": "0xb9bb4be0e10011e99b6800a0c6000009",
    "menu_index": 4,
    "menu_visible": true,
    "name": "Deployer Console",
    "description": "",
    "intro": "",
    "replaces_page_selector": null,
    "created_by_user_selector": "0x31000000000000000000000000000000",
    "created_on": "2019-11-10 18:30:04",
    "modified_by_user_selector": "0x31000000000000000000000000000000",
    "modified_on": "2019-11-22 15:13:52",
    "contents": {
        "widget_type": "Console",
        "object_alias": "exface.Core.ACTION",
        "allowed_commands": [
            "\/action axenox.Deployer:.*\/i",
            "\/dep.*\/"
        ],
        "start_commands": [
            "action list axenox.Deployer",
            "dep"
        ],
        "working_directory_path": "vendor\/bin"
    }
}